README.md
setup.py
rkNN_imputer/__init__.py
rkNN_imputer/rkNN.py
rkNN_imputer.egg-info/PKG-INFO
rkNN_imputer.egg-info/SOURCES.txt
rkNN_imputer.egg-info/dependency_links.txt
rkNN_imputer.egg-info/top_level.txt