Metadata-Version: 1.1
Name: rkNN-imputer
Version: 1.2.5
Summary: Ranking and kNN imputation algorithm
Home-page: https://github.com/LBcoding/ranking-kNN-imputation
Author: Lorenzo Beretta
Author-email: lorberimm@hotmail.com
License: UNKNOWN
Platform: UNKNOWN
Classifier: Programming Language :: Python :: 3
Classifier: License :: OSI Approved :: MIT License
Classifier: Operating System :: OS Independent
